contentai_metadata_flatten/__init__.py
contentai_metadata_flatten/_version.py
contentai_metadata_flatten/main.py
contentai_metadata_flatten/data/templates/metadataEvent.schema.json
contentai_metadata_flatten/data/templates/wbTimeTaggedMetadata.json
contentai_metadata_flatten/generators/__init__.py
contentai_metadata_flatten/generators/flattened_csv.py
contentai_metadata_flatten/generators/wbTimeTaggedMetadata.py
contentai_metadata_flatten/parsers/__init__.py
contentai_metadata_flatten/parsers/aws_rekognition_face_collection.py
contentai_metadata_flatten/parsers/aws_rekognition_video_celebs.py
contentai_metadata_flatten/parsers/aws_rekognition_video_content_moderation.py
contentai_metadata_flatten/parsers/aws_rekognition_video_faces.py
contentai_metadata_flatten/parsers/aws_rekognition_video_labels.py
contentai_metadata_flatten/parsers/aws_rekognition_video_person_tracking.py
contentai_metadata_flatten/parsers/aws_rekognition_video_text_detect.py
contentai_metadata_flatten/parsers/aws_transcribe.py
contentai_metadata_flatten/parsers/azure_videoindexer.py
contentai_metadata_flatten/parsers/comskip_json.py
contentai_metadata_flatten/parsers/detectron2.py
contentai_metadata_flatten/parsers/dsai_activity_classifier.py
contentai_metadata_flatten/parsers/dsai_activity_emotions.py
contentai_metadata_flatten/parsers/dsai_activity_slowfast.py
contentai_metadata_flatten/parsers/dsai_ads_detector.py
contentai_metadata_flatten/parsers/dsai_metadata.py
contentai_metadata_flatten/parsers/dsai_moderation.py
contentai_metadata_flatten/parsers/dsai_moderation_text.py
contentai_metadata_flatten/parsers/dsai_musicnn.py
contentai_metadata_flatten/parsers/dsai_places.py
contentai_metadata_flatten/parsers/dsai_sceneboundary.py
contentai_metadata_flatten/parsers/dsai_yt8m.py
contentai_metadata_flatten/parsers/gcp_videointelligence_explicit_content.py
contentai_metadata_flatten/parsers/gcp_videointelligence_label.py
contentai_metadata_flatten-1.4.1.dist-info/LICENSE
contentai_metadata_flatten-1.4.1.dist-info/METADATA
contentai_metadata_flatten-1.4.1.dist-info/WHEEL
contentai_metadata_flatten-1.4.1.dist-info/entry_points.txt
contentai_metadata_flatten-1.4.1.dist-info/top_level.txt
contentai_metadata_flatten-1.4.1.dist-info/RECORD
