Metadata-Version: 2.1
Name: contentai-metadata-flatten
Version: 1.4.1
Summary: ContentAI Metadata Flattening Service
Home-page: https://gitlab.research.att.com/turnercode/metadata-flatten-extractor
Author: Eric Zavesky
License: Apache
Platform: UNKNOWN
Requires-Python: >=3.6
Requires-Dist: pandas
Requires-Dist: numexpr
Requires-Dist: pytimeparse
Requires-Dist: contentaiextractor (>=1.0.4)
